microscopic/pattern.py
microscopic/queue.py
microscopic/pipelines/pattern_queue.py
microscopic/pipelines/pipelines.py
microscopic/processors/request.py
microscopic/transports/mixins.py
microscopic/transports/pipe.py
microscopic/transports/subprocess.py
microscopic-0.1.0.dist-info/DESCRIPTION.rst
microscopic-0.1.0.dist-info/METADATA
microscopic-0.1.0.dist-info/RECORD
microscopic-0.1.0.dist-info/WHEEL
microscopic-0.1.0.dist-info/metadata.json
microscopic-0.1.0.dist-info/pbr.json
microscopic-0.1.0.dist-info/top_level.txt
