Metadata-Version: 2.0
Name: microscopic
Version: 0.1.0
Summary: over-engineered concurrent tiny-url generator
Home-page: http://microscopic.readthedocs.io/
Author: Zack Buhman
Author-email: zack@buhman.org
License: UNKNOWN
Platform: UNKNOWN
Classifier: Development Status :: 5 - Production/Stable
Classifier: Intended Audience :: Developers
Classifier: License :: OSI Approved :: GNU Lesser General Public License v3 or later (LGPLv3+)
Classifier: Operating System :: POSIX :: Linux
Classifier: Programming Language :: Python
Classifier: Programming Language :: Python :: 3 :: Only
Classifier: Programming Language :: Python :: 3.6
Requires-Dist: aiohttp (>=2.1.0)
Requires-Dist: regex (>=2017.5.26)
